README.md
setup.py
findtools.egg-info/PKG-INFO
findtools.egg-info/SOURCES.txt
findtools.egg-info/dependency_links.txt
findtools.egg-info/top_level.txt
src/findtools/__init__.py
src/findtools/core.py
src/findtools/find_files.py