Metadata-Version: 2.1
Name: findtools
Version: 1.1.0
Summary: Python implementation of GNU Findutils
Home-page: https://github.com/ewiger/findtools
Author: Yauhen Yakimovich
Author-email: eugeny.yakimovitch@gmail.com
License: GPL
Download-URL: https://github.com/ewiger/findtools/tarball/master
Platform: UNKNOWN
